versionfield/__init__.py
versionfield/apps.py
versionfield/constants.py
versionfield/fields.py
versionfield/forms.py
versionfield/models.py
versionfield/tests.py
versionfield/utils.py
versionfield/version.py
versionfield/widgets.py
versionfield/static/django-versionfield/css/bootstrap-theme.css
versionfield/static/django-versionfield/css/bootstrap-theme.css.map
versionfield/static/django-versionfield/css/bootstrap-theme.min.css
versionfield/static/django-versionfield/css/bootstrap-theme.min.css.map
versionfield/static/django-versionfield/css/bootstrap.css
versionfield/static/django-versionfield/css/bootstrap.css.map
versionfield/static/django-versionfield/css/bootstrap.min.css
versionfield/static/django-versionfield/css/bootstrap.min.css.map
versionfield/static/django-versionfield/fonts/glyphicons-halflings-regular.eot
versionfield/static/django-versionfield/fonts/glyphicons-halflings-regular.svg
versionfield/static/django-versionfield/fonts/glyphicons-halflings-regular.ttf
versionfield/static/django-versionfield/fonts/glyphicons-halflings-regular.woff
versionfield/static/django-versionfield/fonts/glyphicons-halflings-regular.woff2
versionfield/static/django-versionfield/js/bootstrap.js
versionfield/static/django-versionfield/js/bootstrap.min.js
versionfield/static/django-versionfield/js/jquery-3.5.1.min.js
versionfield/templates/admin/django-versionfield/widgets/version-field.html
django_versionfield-1.0.3.dist-info/LICENSE
django_versionfield-1.0.3.dist-info/METADATA
django_versionfield-1.0.3.dist-info/WHEEL
django_versionfield-1.0.3.dist-info/top_level.txt
django_versionfield-1.0.3.dist-info/RECORD
